README.rst
setup.py
dota2win/__init__.py
dota2win/dota2.hero.name.txt
dota2win/dota2win
dota2win.egg-info/PKG-INFO
dota2win.egg-info/SOURCES.txt
dota2win.egg-info/dependency_links.txt
dota2win.egg-info/top_level.txt