Metadata-Version: 1.1
Name: dota2win
Version: 0.14
Summary: Win in Dota2
Home-page: www.calyx.biz
Author: Yamol
Author-email: xlccalyx@qq.com
License: GPLv3
Download-URL: https://pypi.python.org/pypi/dota2win
Keywords: dota 2 hero
Platform: UNKNOWN
Classifier: Development Status :: 3 - Alpha
Classifier: Intended Audience :: Developers
Classifier: Topic :: Software Development :: Build Tools
Classifier: License :: OSI Approved :: GNU General Public License v3 (GPLv3)
Classifier: Programming Language :: Python :: 2.7
